tf_sprinkles
