Metadata-Version: 2.1
Name: tf-sprinkles
Version: 1.1.3
Summary: A fast and efficient implimentation of progressive sprinkles augmentation.
Home-page: https://github.com/Engineero/tf_sprinkles
Author: Engineero
Author-email: engineerolabs@gmail.com
License: UNKNOWN
Project-URL: Documentation, https://engineero.github.io/tf_sprinkles
Project-URL: Source, https://github.com/Engineero/tf_sprinkles
Project-URL: Tracker, https://github.com/Engineero/tf_sprinkles/issues
Keywords: augmentation sprinkles tensorflow
Platform: UNKNOWN
Classifier: Development Status :: 5 - Production/Stable
Classifier: Environment :: Console
Classifier: Intended Audience :: Developers
Classifier: Intended Audience :: Science/Research
Classifier: License :: OSI Approved :: MIT License
Classifier: Natural Language :: English
Classifier: Operating System :: OS Independent
Classifier: Programming Language :: Python
Classifier: Programming Language :: Python :: 3.7
Classifier: Topic :: Scientific/Engineering
Classifier: Topic :: Scientific/Engineering :: Artificial Intelligence
Classifier: Topic :: Utilities
